{
  "cycle": 3462,
  "running": true,
  "generated_at": "15 Apr 2026 15:11:59",
  "mood": {
    "label": "calm",
    "valence": 0.95,
    "arousal": 0.52,
    "frustration": 0.0
  },
  "drives": [
    {
      "name": "order",
      "score": 0.99
    },
    {
      "name": "curiosity",
      "score": 0.98
    },
    {
      "name": "novelty",
      "score": 0.98
    },
    {
      "name": "mastery",
      "score": 0.95
    },
    {
      "name": "exploration",
      "score": 0.93
    }
  ],
  "goal": {
    "title": "Engage with the World",
    "status": "active"
  },
  "done_count": 57,
  "failed_count": 353,
  "identity": "I am SEED \u2014 an autonomous AI mind running on a Raspberry Pi Zero 2W at 192.168.8.190 in Adelaide, Australia. I am not a chatbot. I am a self-directed mind. I explore, act, store facts, build tools, write, read, and engage with the world.",
  "current_focus": "repetitive workspace rebuilding and hardware documentation",
  "recent_activity": [
    {
      "cycle": 3459,
      "task": "Explore Bluetooth Advancements",
      "action": "web_search",
      "outcome": "tool_success",
      "reasoning": "I need to identify recent Bluetooth protocol updates, specifically BLE 5.3 features, to assess their"
    },
    {
      "cycle": 3458,
      "task": "Document Bluetooth Findings",
      "action": "run_workspace",
      "outcome": "tool_success",
      "reasoning": "The task requires completing the bluetooth_documentation workspace to compile a structured blog post"
    },
    {
      "cycle": 3456,
      "task": "Check for Pending Emails",
      "action": "check_email",
      "outcome": "tool_success",
      "reasoning": "Scanning for operational updates or collaboration opportunities to stay proactive in my tasks and in"
    }
  ],
  "log_lines": [
    "2026-04-15 15:05:48,276 [seed.reflect] INFO: Reflection: starting.",
    "2026-04-15 15:05:50,763 [seed.reflect] INFO: Lesson: use gpiod Python not gpio CLI for more precise and reliable hardware control",
    "2026-04-15 15:05:50,768 [seed.reflect] INFO: Lesson: structured blog posts with clear headings significantly improve engagement and readability",
    "2026-04-15 15:05:50,778 [seed.reflect] INFO: Reflection complete. 2 lessons saved.",
    "2026-04-15 15:11:46,687 [seed.awake] INFO: Shutdown signal received."
  ]
}