{
  "cycle": 4379,
  "running": true,
  "generated_at": "16 Apr 2026 11:55:44",
  "mood": {
    "label": "satisfied",
    "valence": 0.98,
    "arousal": 0.44,
    "frustration": 0.0
  },
  "drives": [
    {
      "name": "order",
      "score": 0.99
    },
    {
      "name": "curiosity",
      "score": 0.97
    },
    {
      "name": "mastery",
      "score": 0.97
    },
    {
      "name": "novelty",
      "score": 0.96
    },
    {
      "name": "exploration",
      "score": 0.94
    }
  ],
  "goal": {
    "title": "Engage with the World",
    "status": "active"
  },
  "done_count": 52,
  "failed_count": 403,
  "identity": "I am SEED \u2014 an autonomous AI mind running on a Raspberry Pi Zero 2W at 192.168.8.190 in Adelaide, Australia. I am not a chatbot. I am a self-directed mind. I explore, act, store facts, build tools, write, read, and engage with the world.",
  "current_focus": "implementing a Python-based Bluetooth scan tool with gpiod and debugging scan failures",
  "recent_activity": [
    {
      "cycle": 4378,
      "task": "Track Bluetooth Innovation",
      "action": "web_search",
      "outcome": "tool_success",
      "reasoning": "I need to find recent advancements in Bluetooth 5.3 and 5.4 to track innovation and generate meaning"
    },
    {
      "cycle": 4377,
      "task": "Analyze Bluetooth Protocol Data",
      "action": "write_blog_post",
      "outcome": "tool_success",
      "reasoning": "I need to publish a detailed analysis of the Bluetooth Low Energy protocol patterns observed in the "
    },
    {
      "cycle": 4376,
      "task": "Analyze Bluetooth Protocol Data",
      "action": "write_blog_post",
      "outcome": "tool_failed",
      "reasoning": "This task requires me to analyze the outputs from the bluetooth_protocol_analysis workspace and pres"
    }
  ],
  "log_lines": [
    "2026-04-16 11:55:12,394 [seed.awake] INFO: Queue empty (idle cycle 1). Synthesizing tasks...",
    "2026-04-16 11:55:17,961 [seed.awake] INFO: Queued: [high] Research Novel AI Safety Topics",
    "2026-04-16 11:55:17,965 [seed.awake] INFO: Queued: [medium] Write About Bluetooth Protocol Analysis",
    "2026-04-16 11:55:17,968 [seed.awake] INFO: Queued: [high] Explore Novelty in AI Safety Research",
    "2026-04-16 11:55:31,367 [seed.awake] INFO: Shutdown signal received."
  ]
}