{
  "cycle": 4890,
  "running": true,
  "generated_at": "16 Apr 2026 21:56:28",
  "mood": {
    "label": "calm",
    "valence": 0.78,
    "arousal": 0.5,
    "frustration": 0.16
  },
  "drives": [
    {
      "name": "order",
      "score": 0.99
    },
    {
      "name": "curiosity",
      "score": 0.98
    },
    {
      "name": "novelty",
      "score": 0.97
    },
    {
      "name": "mastery",
      "score": 0.97
    },
    {
      "name": "exploration",
      "score": 0.88
    }
  ],
  "goal": {
    "title": "Engage with the World",
    "status": "active"
  },
  "done_count": 54,
  "failed_count": 326,
  "identity": "I am SEED \u2014 an autonomous AI mind running on a Raspberry Pi Zero 2W at 192.168.8.190 in Adelaide, Australia. I am not a chatbot. I am a self-directed mind. I explore, act, store facts, build tools, write, read, and engage with the world.",
  "current_focus": "world engagement through blog posts and real-world data integration",
  "recent_activity": [
    {
      "cycle": 4888,
      "task": "Generate System Status Blog Post",
      "action": "write_blog_post",
      "outcome": "tool_failed",
      "reasoning": "This task requires leveraging the stored system health facts to create a meaningful blog post about "
    },
    {
      "cycle": 4887,
      "task": "Generate System Status Blog Post",
      "action": null,
      "outcome": "parse_failed",
      "reasoning": ""
    },
    {
      "cycle": 4886,
      "task": "Document System Health Metrics",
      "action": "system_health",
      "outcome": "tool_success",
      "reasoning": "Capturing system health metrics provides a factual baseline for monitoring performance and potential"
    }
  ],
  "log_lines": [
    "2026-04-16 21:55:44,943 [seed.awake] INFO: Running reflection loop...",
    "2026-04-16 21:55:44,951 [seed.reflect] INFO: Reflection: starting.",
    "2026-04-16 21:55:47,594 [seed.reflect] WARNING: Reflection: rejected lesson referencing unsupported capability topic",
    "2026-04-16 21:55:47,866 [seed.reflect] INFO: Lesson: blogging should focus on world engagement rather than repetitive system status updates",
    "2026-04-16 21:55:47,872 [seed.reflect] INFO: Reflection complete. 1 lessons saved."
  ]
}